guimadeeasy
