Metadata-Version: 1.0
Name: guimadeeasy
Version: 1.3
Summary: this is just a fun challenge for my friend
Home-page: UNKNOWN
Author: UNKNOWN
Author-email: UNKNOWN
License: UNKNOWN
Platform: UNKNOWN
